macml/CoreML.py
macml/LSM.py
macml/MLCompute.py
macml/NaturalLanguage.py
macml/SoundAnalysis.py
macml/Speech.py
macml/Vision.py
macml/__init__.py
macml/utilities.py
tests/__init__.py
tests/test_textedit.py
macml-0.0.1.dist-info/LICENSE
macml-0.0.1.dist-info/METADATA
macml-0.0.1.dist-info/WHEEL
macml-0.0.1.dist-info/top_level.txt
macml-0.0.1.dist-info/RECORD
